Metadata-Version: 2.1
Name: egancschallengeset3
Version: 0.0.1
Summary: egancschallengeset3
Home-page: 
Author: caden
Requires-Python: >=3.7
License-File: LICENSE.rst
